{
  "comments": {
    // symbol used for single line comment. Remove this entry if your language does not support line comments
    "lineComment": "!"
    // symbols used for start and end a block comment. Remove this entry if your language does not support block comments
    //"blockComment": [ "!*", "*!" ]
  },
  // symbols used as brackets
  "brackets": [
    ["{", "}"],
    ["[", "]"],
    ["(", ")"]
  ],
  // symbols that are auto closed when typing
  "autoClosingPairs": [
    ["{", "}"],
    ["[", "]"],
    ["(", ")"],
    ["\"", "\""],
    ["'", "'"]
  ],
  // symbols that that can be used to surround a selection
  "surroundingPairs": [
    ["{", "}"],
    ["[", "]"],
    ["(", ")"],
    ["\"", "\""],
    ["'", "'"]
  ],
  "wordPattern": "(^\\s*!.*)|(^\\s*\\b(plugin)\\b)|(^\\s*>>(\\s)?)|(\\S*\\.plugin\\.inc)|(?<=plugin\\.)\\b(start|revision|apl|expand|switch|version|prereq|header|libgen|lib|dbupdater|exe|rootexe|files|segments|branch|oel|event|end)\\b|(\\d+\\.\\d+\\.\\d+)|(\\d+\\.\\d+)"
}
